flask_authentic/__init__.py
flask_authentic/__main__.py
flask_authentic/cli.py
flask_authentic/config.py
flask_authentic/decorators.py
flask_authentic/account/__init__.py
flask_authentic/account/blueprint.py
flask_authentic/account/views.py
flask_authentic-0.0.11.dist-info/AUTHORS.rst
flask_authentic-0.0.11.dist-info/LICENSE
flask_authentic-0.0.11.dist-info/METADATA
flask_authentic-0.0.11.dist-info/WHEEL
flask_authentic-0.0.11.dist-info/entry_points.txt
flask_authentic-0.0.11.dist-info/top_level.txt
flask_authentic-0.0.11.dist-info/RECORD
