Metadata-Version: 2.1
Name: flask-authentic
Version: 0.0.11
Summary: Flask Authentic Extension
Home-page: https://github.com/proteanhq/flask-authentic
Author: Subhash Bhushan C
Author-email: subhash@team8solutions.com
License: BSD 3-Clause License
Platform: UNKNOWN
Classifier: Development Status :: 2 - Pre-Alpha
Classifier: Framework :: Flask
Classifier: Intended Audience :: Developers
Classifier: License :: OSI Approved :: BSD License
Classifier: Operating System :: Unix
Classifier: Operating System :: POSIX :: Linux
Classifier: Operating System :: OS/2
Classifier: Programming Language :: Python
Classifier: Programming Language :: Python :: 3.7
Classifier: Programming Language :: Python :: 3 :: Only
Classifier: Topic :: Database
Classifier: Topic :: Software Development :: Libraries
Classifier: Topic :: Software Development :: Libraries :: Application Frameworks
Classifier: Topic :: Software Development :: Libraries :: Python Modules
Requires-Dist: click (==7.0)
Requires-Dist: protean (==0.0.11)
Requires-Dist: authentic (==0.0.11)
Requires-Dist: protean-flask (==0.0.11)
